pyreprint/__init__.py
pyreprint/_version.py
pyreprint/config.py
pyreprint/py.typed
pyreprint/core/__init__.py
pyreprint/core/capture.py
pyreprint/core/decorators.py
pyreprint/core/printer.py
pyreprint/formatting/__init__.py
pyreprint/formatting/html.py
pyreprint/formatting/repr.py
pyreprint/integrations/__init__.py
pyreprint/integrations/pprint.py
pyreprint/integrations/rich.py
pyreprint/styles/__init__.py
pyreprint/styles/builtins.py
pyreprint/styles/loader.py
pyreprint/styles/registry.py
pyreprint-0.1.0.dist-info/METADATA
pyreprint-0.1.0.dist-info/WHEEL
pyreprint-0.1.0.dist-info/licenses/LICENSE
pyreprint-0.1.0.dist-info/RECORD
