Metadata-Version: 2.4
Name: pyreprint
Version: 0.1.0
Summary: Enhanced print() with decorators, formatting, and style patterns
Project-URL: Homepage, https://github.com/ColinConwell/PyRePrint
Project-URL: Documentation, https://colinconwell.github.io/PyRePrint
Project-URL: Repository, https://github.com/ColinConwell/PyRePrint
Project-URL: Issues, https://github.com/ColinConwell/PyRePrint/issues
Author-email: Developer <developer@dev.com>
License-Expression: GPL-3.0-or-later
License-File: LICENSE
Keywords: decorators,formatting,jupyter,output,print,rich,terminal
Classifier: Development Status :: 4 - Beta
Classifier: Environment :: Console
Classifier: Framework :: Jupyter
Classifier: Intended Audience :: Developers
Classifier: License :: OSI Approved :: GNU General Public License v3 or later (GPLv3+)
Classifier: Operating System :: OS Independent
Classifier: Programming Language :: Python :: 3
Classifier: Programming Language :: Python :: 3.10
Classifier: Topic :: Software Development :: Libraries :: Python Modules
Requires-Python: >=3.8
Requires-Dist: pyyaml>=6.0
Requires-Dist: rich>=13.0.0
Requires-Dist: tomli>=2.0.0; python_version < '3.11'
Provides-Extra: dev
Requires-Dist: black>=23.0; extra == 'dev'
Requires-Dist: mkdocs-material>=9.0; extra == 'dev'
Requires-Dist: mkdocs>=1.5; extra == 'dev'
Requires-Dist: mkdocstrings[python]>=0.24; extra == 'dev'
Requires-Dist: mypy>=1.0; extra == 'dev'
Requires-Dist: pytest-cov>=4.0; extra == 'dev'
Requires-Dist: pytest>=7.0; extra == 'dev'
Requires-Dist: ruff>=0.1.0; extra == 'dev'
